Metadata-Version: 2.1
Name: odoo12-addon-server-env-printing-server
Version: 12.0.1.0.0.99.dev4
Summary: Server Environment for Printing Server
Home-page: https://github.com/OCA/report-print-send
Author: Camptocamp, Odoo Community Association (OCA)
Author-email: support@odoo-community.org
License: AGPL-3
Platform: UNKNOWN
Classifier: Programming Language :: Python
Classifier: Framework :: Odoo
Classifier: Framework :: Odoo :: 12.0
Classifier: License :: OSI Approved :: GNU Affero General Public License v3
Requires-Python: >=3.5
Requires-Dist: odoo12-addon-base-report-to-printer
Requires-Dist: odoo12-addon-server-environment
Requires-Dist: odoo <12.1dev,>=12.0a
